setup.py
bin/nerocli
bin/nerogui
neronet/__init__.py
neronet/config_parser.py
neronet/core.py
neronet/daemon.py
neronet/design.py
neronet/experiment.py
neronet/nerocli.py
neronet/nerogui.py
neronet/nerokid
neronet/nerokid.py
neronet/nerokid_test.py
neronet/neroman.py
neronet/neromum
neronet/neromum.py
neronet/neromum_test.py
neronet/node.py
neronet/version.py
neronet.egg-info/PKG-INFO
neronet.egg-info/SOURCES.txt
neronet.egg-info/dependency_links.txt
neronet.egg-info/requires.txt
neronet.egg-info/top_level.txt
neronet.egg-info/zip-safe
test/test_cli.py
test/test_experiment.py
test/test_specify_clusters.py
test/test_specify_experiments.py
test/test_status_report.py