Metadata-Version: 1.1
Name: neronet
Version: 0.3.3
Summary: A tool for managing multiple computational experiments.
Home-page: http://github.com/smarisa/neronet
Author: The neronet team
Author-email: samuel.marisa@aalto.fi
License: MIT
Platform: unix
Classifier: Programming Language :: Python
Classifier: Development Status :: 2 - Pre-Alpha
Classifier: Natural Language :: English
Classifier: Environment :: Console
Classifier: Intended Audience :: End Users/Desktop
Classifier: License :: OSI Approved :: MIT License
Classifier: Operating System :: Unix
Classifier: Topic :: Software Development :: Libraries :: Python Modules
